validatetoken/__init__.py
validatetoken/echo/__init__.py
validatetoken/echo/__main__.py
validatetoken/echo/service.py
validatetoken/middleware/__init__.py
validatetoken/middleware/validatetoken.py
validatetoken/tests/__init__.py
validatetoken/tests/unit/__init__.py
validatetoken/tests/unit/middleware/__init__.py
validatetoken/tests/unit/middleware/test_validatetoken.py
validatetoken-0.2.0.dist-info/AUTHORS
validatetoken-0.2.0.dist-info/LICENSE
validatetoken-0.2.0.dist-info/METADATA
validatetoken-0.2.0.dist-info/WHEEL
validatetoken-0.2.0.dist-info/entry_points.txt
validatetoken-0.2.0.dist-info/pbr.json
validatetoken-0.2.0.dist-info/top_level.txt
validatetoken-0.2.0.dist-info/RECORD
